zsp_arl_dm/libzsp-arl-dm.so
zsp_arl_dm/core.cpython-38-x86_64-linux-gnu.so
zsp_arl_dm/core.pxd
zsp_arl_dm/decl.pxd
zsp_arl_dm/pkginfo.py
zsp_arl_dm/val_ref_to_py_val.py
zsp_arl_dm/__build_num__.py
zsp_arl_dm/__init__.py
zsp_arl_dm/py_val_to_val_ref.py
zsp_arl_dm/share/include/TypeFieldAddrClaim.cpp
zsp_arl_dm/share/include/TypeFieldAddrClaim.h
zsp_arl_dm/share/include/zsp/arl/dm/IModelComponentTreeData.h
zsp_arl_dm/share/include/zsp/arl/dm/IModelFieldRegGroupRef.h
zsp_arl_dm/share/include/zsp/arl/dm/IModelActivitySequence.h
zsp_arl_dm/share/include/zsp/arl/dm/IDataTypeAddrHandle.h
zsp_arl_dm/share/include/zsp/arl/dm/loader.h
zsp_arl_dm/share/include/zsp/arl/dm/IDataTypeActivityScope.h
zsp_arl_dm/share/include/zsp/arl/dm/IDataTypeActivityParallel.h
zsp_arl_dm/share/include/zsp/arl/dm/ITypeFieldExecutorClaim.h
zsp_arl_dm/share/include/zsp/arl/dm/ITypeProcStmtVarDecl.h
zsp_arl_dm/share/include/zsp/arl/dm/ITypeModelDumper.h
zsp_arl_dm/share/include/zsp/arl/dm/ITypeFieldRegGroupArr.h
zsp_arl_dm/share/include/zsp/arl/dm/ITypeProcStmtIfClause.h
zsp_arl_dm/share/include/zsp/arl/dm/IDataTypeActivitySequence.h
zsp_arl_dm/share/include/zsp/arl/dm/IModelFieldExecutor.h
zsp_arl_dm/share/include/zsp/arl/dm/IDataTypeFunctionImport.h
zsp_arl_dm/share/include/zsp/arl/dm/ITypeFieldPool.h
zsp_arl_dm/share/include/zsp/arl/dm/IDataTypePureComponent.h
zsp_arl_dm/share/include/zsp/arl/dm/IModelFieldInOut.h
zsp_arl_dm/share/include/zsp/arl/dm/IDataTypeRegGroup.h
zsp_arl_dm/share/include/zsp/arl/dm/IDataTypeArlStruct.h
zsp_arl_dm/share/include/zsp/arl/dm/IDataTypeActivityTraverse.h
zsp_arl_dm/share/include/zsp/arl/dm/IDataTypeReg.h
zsp_arl_dm/share/include/zsp/arl/dm/ITypeProcStmtScope.h
zsp_arl_dm/share/include/zsp/arl/dm/ITypeFieldAddrClaimTransparent.h
zsp_arl_dm/share/include/zsp/arl/dm/IModelEvalIterator.h
zsp_arl_dm/share/include/zsp/arl/dm/ITypeProcStmtWhile.h
zsp_arl_dm/share/include/zsp/arl/dm/ITypeFieldRegGroup.h
zuspec_arl_dm-0.0.5.13094843353.dist-info/LICENSE
zuspec_arl_dm-0.0.5.13094843353.dist-info/WHEEL
zuspec_arl_dm-0.0.5.13094843353.dist-info/RECORD
zuspec_arl_dm-0.0.5.13094843353.dist-info/top_level.txt
zuspec_arl_dm-0.0.5.13094843353.dist-info/entry_points.txt
zuspec_arl_dm-0.0.5.13094843353.dist-info/METADATA
