Metadata-Version: 2.1
Name: zuspec-arl-dm
Version: 0.0.5.13094843353
Summary: Core ARL data model library
Home-page: https://github.com/zuspec/zuspec-arl-dm
Author: Matthew Ballance
Author-email: matt.ballance@gmail.com
License: Apache 2.0
Keywords: SystemVerilog,Verilog,RTL,Python
License-File: LICENSE
Requires-Dist: vsc-dm
Requires-Dist: debug-mgr
